oceanclimate_tools/__init__.py
oceanclimate_tools/geo.py
oceanclimate_tools/pressure.py
oceanclimate_tools/salinity.py
oceanclimate_tools/temperature.py
oceanclimate_tools/wind.py
oceanclimate_tools-0.1.1.dist-info/licenses/LICENSE
oceanclimate_tools-0.1.1.dist-info/METADATA
oceanclimate_tools-0.1.1.dist-info/WHEEL
oceanclimate_tools-0.1.1.dist-info/top_level.txt
oceanclimate_tools-0.1.1.dist-info/RECORD
