Metadata-Version: 2.4
Name: oceanclimate-tools
Version: 0.1.1
Summary: Beginner-friendly ocean & climate conversion utilities.
Author: Bobbie Williams
Classifier: Programming Language :: Python :: 3
Classifier: Programming Language :: Python :: 3.12
Classifier: Programming Language :: Python :: 3.13
Classifier: License :: OSI Approved :: MIT License
Classifier: Intended Audience :: Science/Research
Classifier: Topic :: Scientific/Engineering :: Atmospheric Science
Requires-Python: >=3.12
License-File: LICENSE
Dynamic: license-file
